aitest_tool.py
app/aitest_application.py
aitest_cli-0.2.28.dist-info/LICENSE
aitest_cli-0.2.28.dist-info/METADATA
aitest_cli-0.2.28.dist-info/WHEEL
aitest_cli-0.2.28.dist-info/entry_points.txt
aitest_cli-0.2.28.dist-info/top_level.txt
aitest_cli-0.2.28.dist-info/RECORD
