Metadata-Version: 2.1
Name: aitest-cli
Version: 0.2.28
Summary: aitest
Home-page: https://github.com/applied-ai-consulting/aiTest--CLI
Author: aitest
Author-email: vishwas@appliedaiconsulting.com
License: MIT License
Platform: UNKNOWN
Classifier: Programming Language :: Python :: 3.8
Classifier: Operating System :: OS Independent
Requires-Python: >=3.7
Requires-Dist: Click (==7.0)
Requires-Dist: prettytable (==3.6.0)
Requires-Dist: requests (==2.30.0)
Requires-Dist: setuptools (==45.2.0)
